aiodistbus/__init__.py
aiodistbus/_log.py
aiodistbus/_loop.py
aiodistbus/cfg.py
aiodistbus/observables.py
aiodistbus/protocols.py
aiodistbus/registry.py
aiodistbus/singleton.py
aiodistbus/timer.py
aiodistbus/utils.py
aiodistbus/version.py
aiodistbus/wrapper.py
aiodistbus/entrypoint/__init__.py
aiodistbus/entrypoint/aentrypoint.py
aiodistbus/entrypoint/dentrypoint.py
aiodistbus/entrypoint/entrypoint.py
aiodistbus/eventbus/__init__.py
aiodistbus/eventbus/aeventbus.py
aiodistbus/eventbus/deventbus.py
aiodistbus/eventbus/eventbus.py
examples/dbus.py
test/__init__.py
test/conftest.py
test/test_bridge.py
test/test_bus.py
test/test_dbus.py
test/test_error.py
test/test_mp.py
test/test_registry.py
test/test_stress.py
test/test_wrapper.py
aiodistbus-0.0.2.dist-info/LICENSE
aiodistbus-0.0.2.dist-info/METADATA
aiodistbus-0.0.2.dist-info/WHEEL
aiodistbus-0.0.2.dist-info/top_level.txt
aiodistbus-0.0.2.dist-info/RECORD
