Metadata-Version: 2.1
Name: aiodistbus
Version: 0.0.2
Summary: ZeroMQ Distributed EventBus for Python
Author-email: Eduardo Davalos <eduardo.davalos.anaya@vanderbilt.edu>, Umesh Timalsina <umesh.timalsina@vanderbilt.edu>
Project-URL: homepath, https://github.com/ChimeraPy/aiodistbus
Project-URL: repository, https://github.com/ChimeraPy/aiodistbus
Keywords: event,bus,distributed,observer,zeromq
Classifier: Programming Language :: Python :: 3
Requires-Python: >3.6
License-File: LICENSE
Requires-Dist: asyncio-atexit
Requires-Dist: pyzmq
Requires-Dist: dataclasses-json
Requires-Dist: aioreactive
Requires-Dist: uvloop ; sys_platform != "win32"
Requires-Dist: winloop ; sys_platform == "win32"
Provides-Extra: test
Requires-Dist: pytest ; extra == 'test'
Requires-Dist: pytest-asyncio ; extra == 'test'
Requires-Dist: pytest-repeat ; extra == 'test'
Requires-Dist: pytest-lazy-fixture ; extra == 'test'
Requires-Dist: pytest-rerunfailures ; extra == 'test'
Requires-Dist: auto-changelog ; extra == 'test'
Requires-Dist: coveralls ; extra == 'test'
Requires-Dist: pre-commit ; extra == 'test'
Requires-Dist: bump2version ; extra == 'test'
